alanpows_pycounter_tools/__init__.py
alanpows_pycounter_tools/alanpows_pycounter_tools.py
alanpows_pycounter_tools/plotting.py
alanpows_pycounter_tools-0.1.0.dist-info/LICENSE
alanpows_pycounter_tools-0.1.0.dist-info/METADATA
alanpows_pycounter_tools-0.1.0.dist-info/WHEEL
alanpows_pycounter_tools-0.1.0.dist-info/RECORD
