Metadata-Version: 2.1
Name: alanpows_pycounter_tools
Version: 0.1.0
Summary: A package to help you count through your texts and understand how many and what words you have!
License: MIT
Author: Alan Powichrowski
Requires-Python: >=3.9,<4.0
Classifier: License :: OSI Approved :: MIT License
Classifier: Programming Language :: Python :: 3
Classifier: Programming Language :: Python :: 3.9
Classifier: Programming Language :: Python :: 3.10
Classifier: Programming Language :: Python :: 3.11
Classifier: Programming Language :: Python :: 3.12
Requires-Dist: matplotlib (>=3.8.2,<4.0.0)
